explict.py
MoreUpdate-1.0.7.dist-info/LICENSE.txt
MoreUpdate-1.0.7.dist-info/METADATA
MoreUpdate-1.0.7.dist-info/WHEEL
MoreUpdate-1.0.7.dist-info/top_level.txt
MoreUpdate-1.0.7.dist-info/RECORD
