Metadata-Version: 2.1
Name: MoreUpdate
Version: 1.0.7
Summary: A library for open Python project
Author: Quanvndev
Author-email: rakis9076@gmail.com
License: UNKNOWN
Keywords: function,setuptools,development
Platform: UNKNOWN
Classifier: Development Status :: 3 - Alpha
Classifier: Intended Audience :: Developers
Classifier: Topic :: Software Development :: Build Tools
Classifier: License :: OSI Approved :: MIT License
Classifier: Programming Language :: Python :: 3.10
Requires-Python: >=3.8
License-File: LICENSE.txt
Requires-Dist: traceback
Requires-Dist: time
Requires-Dist: string
Requires-Dist: random
Requires-Dist: re
Requires-Dist: multiprocessing
Requires-Dist: threading
